neuralactivitycubic/__init__.py
neuralactivitycubic/_modidx.py
neuralactivitycubic/analysis.py
neuralactivitycubic/api.py
neuralactivitycubic/controller.py
neuralactivitycubic/datamodels.py
neuralactivitycubic/input.py
neuralactivitycubic/model.py
neuralactivitycubic/processing.py
neuralactivitycubic/results.py
neuralactivitycubic/view.py
neuralactivitycubic-0.1.5.dist-info/licenses/LICENSE
neuralactivitycubic-0.1.5.dist-info/METADATA
neuralactivitycubic-0.1.5.dist-info/WHEEL
neuralactivitycubic-0.1.5.dist-info/entry_points.txt
neuralactivitycubic-0.1.5.dist-info/top_level.txt
neuralactivitycubic-0.1.5.dist-info/RECORD
