Metadata-Version: 2.4
Name: neuralactivitycubic
Version: 0.1.5
Summary: Computation of local and signal-close-to-noise calcium activity
Home-page: https://github.com/Indoc-Research/NeuralActivityCubic
Author: Dennis Doll
Author-email: ddoll@indocresearch.org
License: AGPL-3.0
Keywords: nbdev jupyter notebook python
Classifier: Development Status :: 4 - Beta
Classifier: Intended Audience :: Science/Research
Classifier: Natural Language :: English
Classifier: Programming Language :: Python :: 3.11
Classifier: Programming Language :: Python :: 3.12
Requires-Python: >=3.11
License-File: LICENSE
Requires-Dist: jupyterlab>=4.4.8
Requires-Dist: ipywidgets>=8.0.4
Requires-Dist: ipyfilechooser>=0.6.0
Requires-Dist: imageio>=2.31.4
Requires-Dist: imageio-ffmpeg>=0.4.9
Requires-Dist: matplotlib>=3.8.0
Requires-Dist: scipy>=1.15.3
Requires-Dist: numpy>=2.2.5
Requires-Dist: pandas>=2.2.1
Requires-Dist: pybaselines>=1.1.0
Requires-Dist: roifile>=2024.5.24
Requires-Dist: shapely>=2.0.1
Requires-Dist: scikit-image>=0.22.0
Requires-Dist: pynwb>=3.0.0
Requires-Dist: fastcore>=1.8.2
Provides-Extra: dev
Requires-Dist: playwright>=1.53.0; extra == "dev"
Dynamic: author
Dynamic: author-email
Dynamic: classifier
Dynamic: description
Dynamic: description-content-type
Dynamic: home-page
Dynamic: keywords
Dynamic: license
Dynamic: license-file
Dynamic: provides-extra
Dynamic: requires-dist
Dynamic: requires-python
Dynamic: summary
